agentskills/__init__.py
agentskills/cli.py
agentskills/errors.py
agentskills/models.py
agentskills/parser.py
agentskills/prompt.py
agentskills/validator.py
skills_ref-0.1.0.dist-info/METADATA
skills_ref-0.1.0.dist-info/WHEEL
skills_ref-0.1.0.dist-info/entry_points.txt
skills_ref-0.1.0.dist-info/licenses/LICENSE
skills_ref-0.1.0.dist-info/RECORD
