Metadata-Version: 2.4
Name: skills-ref
Version: 0.1.0
Summary: Reference library for Agent Skills
Project-URL: Homepage, https://agentskills.io
Project-URL: Documentation, https://agentskills.io
Project-URL: Repository, https://github.com/anthropics/agentskills
Project-URL: Issues, https://github.com/anthropics/agentskills/issues
Author-email: Keith Lazuka <klazuka@anthropic.com>
License-Expression: Apache-2.0
License-File: LICENSE
Keywords: agents,ai,automation,llm,skills
Classifier: Development Status :: 3 - Alpha
Classifier: Intended Audience :: Developers
Classifier: License :: OSI Approved :: Apache Software License
Classifier: Programming Language :: Python :: 3
Classifier: Programming Language :: Python :: 3.11
Classifier: Programming Language :: Python :: 3.12
Classifier: Programming Language :: Python :: 3.13
Classifier: Topic :: Software Development :: Libraries :: Python Modules
Requires-Python: >=3.11
Requires-Dist: click>=8.0
Requires-Dist: strictyaml>=1.7.3
